tolerant/__init__.py
tolerant/toposort.py
tolerant_toposort-1.9.1rc5.dist-info/LICENSE-2.0.txt
tolerant_toposort-1.9.1rc5.dist-info/METADATA
tolerant_toposort-1.9.1rc5.dist-info/WHEEL
tolerant_toposort-1.9.1rc5.dist-info/top_level.txt
tolerant_toposort-1.9.1rc5.dist-info/RECORD
