Metadata-Version: 2.1
Name: tolerant-toposort
Version: 1.9.1rc5
Summary: Implements a topological sort algorithm with ability to tolerate existing but disabled nodes
Author-email: David Turland <david@turland.org>, "Eric V. Smith" <eric@trueblade.com>
License: Apache License Version 2.0
Project-URL: Issues, https://github.com/DavidTurland/tolerant-toposort/issues
Project-URL: Source, https://github.com/DavidTurland/tolerant-toposort
Project-URL: Original, https://pypi.org/project/toposort
Keywords: toposort,graph,tolerant
Classifier: Development Status :: 5 - Production/Stable
Classifier: Intended Audience :: Developers
Classifier: License :: OSI Approved :: Apache Software License
Classifier: Topic :: Software Development :: Libraries :: Python Modules
Classifier: Programming Language :: Python :: 3.8
Classifier: Programming Language :: Python :: 3.9
Classifier: Programming Language :: Python :: 3.10
Requires-Python: >=3
License-File: LICENSE-2.0.txt
Provides-Extra: test
Requires-Dist: pytest (<5.0.0) ; extra == 'test'
Requires-Dist: pytest-cov[all] ; extra == 'test'
Requires-Dist: Flask (<3,>=2) ; extra == 'test'
